aws_recommendation_a11/__init__.py
aws_recommendation_a11/cloudwatch.py
aws_recommendation_a11/cost_estimations.py
aws_recommendation_a11/dynamodb.py
aws_recommendation_a11/ebs.py
aws_recommendation_a11/ec2.py
aws_recommendation_a11/elb.py
aws_recommendation_a11/kms.py
aws_recommendation_a11/rds.py
aws_recommendation_a11/recommendation.py
aws_recommendation_a11/redshift.py
aws_recommendation_a11/s3.py
aws_recommendation_a11/truted_advisor.py
aws_recommendation_a11/utils.py
aws_recommendation_a11-0.0.23.dist-info/LICENCE
aws_recommendation_a11-0.0.23.dist-info/METADATA
aws_recommendation_a11-0.0.23.dist-info/WHEEL
aws_recommendation_a11-0.0.23.dist-info/top_level.txt
aws_recommendation_a11-0.0.23.dist-info/RECORD
